indoxGen/__init__.py
indoxGen/hybrid_synth/__init__.py
indoxGen/hybrid_synth/text_tabular.py
indoxGen/llms/__init__.py
indoxGen/llms/googleai.py
indoxGen/llms/huggingface.py
indoxGen/llms/mistral.py
indoxGen/llms/nerd_token.py
indoxGen/llms/ollama.py
indoxGen/llms/openai.py
indoxGen/synthCore/__init__.py
indoxGen/synthCore/PromptSynthDataGen/__init__.py
indoxGen/synthCore/PromptSynthDataGen/data_from_attribute.py
indoxGen/synthCore/PromptSynthDataGen/data_from_prompt.py
indoxGen/synthCore/PromptSynthDataGen/few_shot_prompt.py
indoxGen/synthCore/SynthDataGenJudgeLLM/__init__.py
indoxGen/synthCore/SynthDataGenJudgeLLM/synthetic_data_generation.py
indoxGen/synthCore/SynthDataGenJudgeLLM/synthetic_data_generation_humanfeedback.py
indoxGen/utils/__init__.py
indoxGen/utils/csv.py
indoxGen/utils/excel.py
indoxGen-0.2.0.dist-info/LICENSE
indoxGen-0.2.0.dist-info/METADATA
indoxGen-0.2.0.dist-info/WHEEL
indoxGen-0.2.0.dist-info/top_level.txt
indoxGen-0.2.0.dist-info/RECORD
