Metadata-Version: 2.1
Name: indoxGen
Version: 0.2.0
Summary: Indox Synthetic Data Generation
Home-page: https://github.com/osllmai/inDox/libs/IndoxGen
Author: nerdstudio
Author-email: ashkan@nematifamilyfundation.onmicrosoft.com
License: AGPL-3.0-or-later
Keywords: AI,deep learning,language models,synthetic data generation,machine learning,NLP
Classifier: Development Status :: 3 - Alpha
Classifier: Intended Audience :: Developers
Classifier: Topic :: Software Development :: Build Tools
Classifier: License :: OSI Approved :: GNU Affero General Public License v3 or later (AGPLv3+)
Classifier: Programming Language :: Python :: 3.9
Classifier: Programming Language :: Python :: 3.10
Classifier: Programming Language :: Python :: 3.11
Classifier: Programming Language :: Python :: 3.12
Requires-Python: >=3.9
License-File: LICENSE
